[
    {
        "text": " Once",
        "timestamp": [
            0.0,
            0.8
        ]
    },
    {
        "text": " upon",
        "timestamp": [
            0.8,
            1.06
        ]
    },
    {
        "text": " a",
        "timestamp": [
            1.06,
            1.24
        ]
    },
    {
        "text": " time,",
        "timestamp": [
            1.24,
            1.42
        ]
    },
    {
        "text": " the",
        "timestamp": [
            1.48,
            1.62
        ]
    },
    {
        "text": " mountains",
        "timestamp": [
            1.62,
            1.96
        ]
    },
    {
        "text": " on",
        "timestamp": [
            1.96,
            2.18
        ]
    },
    {
        "text": " Earth",
        "timestamp": [
            2.18,
            2.3
        ]
    },
    {
        "text": " were",
        "timestamp": [
            2.3,
            2.54
        ]
    },
    {
        "text": " curious",
        "timestamp": [
            2.54,
            2.94
        ]
    },
    {
        "text": " about",
        "timestamp": [
            2.94,
            3.2
        ]
    },
    {
        "text": " the",
        "timestamp": [
            3.2,
            3.4
        ]
    },
    {
        "text": " moon",
        "timestamp": [
            3.4,
            3.58
        ]
    },
    {
        "text": " and",
        "timestamp": [
            3.58,
            3.8
        ]
    },
    {
        "text": " the",
        "timestamp": [
            3.8,
            4.06
        ]
    },
    {
        "text": " sky.",
        "timestamp": [
            4.06,
            4.46
        ]
    },
    {
        "text": " They",
        "timestamp": [
            4.78,
            4.94
        ]
    },
    {
        "text": " had",
        "timestamp": [
            4.94,
            5.22
        ]
    },
    {
        "text": " heard",
        "timestamp": [
            5.22,
            5.64
        ]
    },
    {
        "text": " about",
        "timestamp": [
            5.64,
            6.04
        ]
    },
    {
        "text": " the",
        "timestamp": [
            6.04,
            6.3
        ]
    },
    {
        "text": " moon's",
        "timestamp": [
            6.3,
            6.72
        ]
    },
    {
        "text": " beauty",
        "timestamp": [
            6.72,
            6.96
        ]
    },
    {
        "text": " and",
        "timestamp": [
            6.96,
            7.5
        ]
    },
    {
        "text": " wondered",
        "timestamp": [
            7.5,
            7.86
        ]
    },
    {
        "text": " if",
        "timestamp": [
            7.86,
            8.06
        ]
    },
    {
        "text": " they",
        "timestamp": [
            8.06,
            8.24
        ]
    },
    {
        "text": " could",
        "timestamp": [
            8.24,
            8.52
        ]
    },
    {
        "text": " ever",
        "timestamp": [
            8.52,
            8.84
        ]
    },
    {
        "text": " reach",
        "timestamp": [
            8.84,
            9.14
        ]
    },
    {
        "text": " it.",
        "timestamp": [
            9.14,
            9.5
        ]
    },
    {
        "text": " Do",
        "timestamp": [
            10.74,
            10.92
        ]
    },
    {
        "text": " you",
        "timestamp": [
            10.92,
            11.1
        ]
    },
    {
        "text": " think",
        "timestamp": [
            11.1,
            11.3
        ]
    },
    {
        "text": " we",
        "timestamp": [
            11.3,
            11.5
        ]
    },
    {
        "text": " can",
        "timestamp": [
            11.5,
            11.74
        ]
    },
    {
        "text": " reach",
        "timestamp": [
            11.74,
            12.18
        ]
    },
    {
        "text": " the",
        "timestamp": [
            12.18,
            12.5
        ]
    },
    {
        "text": " moon?",
        "timestamp": [
            12.5,
            12.96
        ]
    },
    {
        "text": " Yeah,",
        "timestamp": [
            13.3,
            13.62
        ]
    },
    {
        "text": " I",
        "timestamp": [
            13.62,
            13.82
        ]
    },
    {
        "text": " think",
        "timestamp": [
            13.82,
            14.08
        ]
    },
    {
        "text": " so.",
        "timestamp": [
            14.08,
            14.5
        ]
    },
    {
        "text": " One",
        "timestamp": [
            15.72,
            16.0
        ]
    },
    {
        "text": " night,",
        "timestamp": [
            16.0,
            16.46
        ]
    },
    {
        "text": " they",
        "timestamp": [
            16.62,
            16.9
        ]
    },
    {
        "text": " decided",
        "timestamp": [
            16.9,
            17.38
        ]
    },
    {
        "text": " to",
        "timestamp": [
            17.38,
            17.76
        ]
    },
    {
        "text": " climb",
        "timestamp": [
            17.76,
            18.06
        ]
    },
    {
        "text": " higher",
        "timestamp": [
            18.06,
            18.38
        ]
    },
    {
        "text": " and",
        "timestamp": [
            18.38,
            18.74
        ]
    },
    {
        "text": " higher",
        "timestamp": [
            18.74,
            19.04
        ]
    },
    {
        "text": " in",
        "timestamp": [
            19.04,
            19.3
        ]
    },
    {
        "text": " hopes",
        "timestamp": [
            19.3,
            19.54
        ]
    },
    {
        "text": " of",
        "timestamp": [
            19.54,
            19.86
        ]
    },
    {
        "text": " meeting",
        "timestamp": [
            19.86,
            20.16
        ]
    },
    {
        "text": " it.",
        "timestamp": [
            20.16,
            20.64
        ]
    },
    {
        "text": " As",
        "timestamp": [
            20.78,
            21.12
        ]
    },
    {
        "text": " the",
        "timestamp": [
            21.12,
            21.32
        ]
    },
    {
        "text": " mountains",
        "timestamp": [
            21.32,
            21.66
        ]
    },
    {
        "text": " climbed,",
        "timestamp": [
            21.66,
            22.16
        ]
    },
    {
        "text": " they",
        "timestamp": [
            22.58,
            22.82
        ]
    },
    {
        "text": " grew",
        "timestamp": [
            22.82,
            23.04
        ]
    },
    {
        "text": " tired",
        "timestamp": [
            23.04,
            23.52
        ]
    },
    {
        "text": " and",
        "timestamp": [
            23.52,
            23.82
        ]
    },
    {
        "text": " discouraged.",
        "timestamp": [
            23.82,
            24.58
        ]
    },
    {
        "text": " They",
        "timestamp": [
            25.0,
            25.2
        ]
    },
    {
        "text": " thought",
        "timestamp": [
            25.2,
            25.4
        ]
    },
    {
        "text": " they",
        "timestamp": [
            25.4,
            25.52
        ]
    },
    {
        "text": " would",
        "timestamp": [
            25.52,
            25.7
        ]
    },
    {
        "text": " never",
        "timestamp": [
            25.7,
            25.92
        ]
    },
    {
        "text": " reach",
        "timestamp": [
            25.92,
            26.18
        ]
    },
    {
        "text": " the",
        "timestamp": [
            26.18,
            26.4
        ]
    },
    {
        "text": " moon",
        "timestamp": [
            26.4,
            26.64
        ]
    },
    {
        "text": " and",
        "timestamp": [
            26.64,
            27.06
        ]
    },
    {
        "text": " started",
        "timestamp": [
            27.06,
            27.34
        ]
    },
    {
        "text": " to",
        "timestamp": [
            27.34,
            27.74
        ]
    },
    {
        "text": " doubt",
        "timestamp": [
            27.74,
            27.88
        ]
    },
    {
        "text": " themselves.",
        "timestamp": [
            27.88,
            28.54
        ]
    },
    {
        "text": " But",
        "timestamp": [
            28.54,
            28.98
        ]
    },
    {
        "text": " just",
        "timestamp": [
            28.98,
            29.3
        ]
    },
    {
        "text": " then",
        "timestamp": [
            29.3,
            29.5
        ]
    },
    {
        "text": " an",
        "timestamp": [
            29.5,
            29.7
        ]
    },
    {
        "text": " old",
        "timestamp": [
            29.7,
            29.88
        ]
    },
    {
        "text": " man",
        "timestamp": [
            29.88,
            30.04
        ]
    },
    {
        "text": " appeared",
        "timestamp": [
            30.04,
            30.46
        ]
    },
    {
        "text": " and",
        "timestamp": [
            30.46,
            30.78
        ]
    },
    {
        "text": " asked",
        "timestamp": [
            30.78,
            31.02
        ]
    },
    {
        "text": " them",
        "timestamp": [
            31.02,
            31.4
        ]
    },
    {
        "text": " what",
        "timestamp": [
            31.4,
            31.66
        ]
    },
    {
        "text": " was",
        "timestamp": [
            31.66,
            32.02
        ]
    },
    {
        "text": " wrong.",
        "timestamp": [
            32.02,
            32.46
        ]
    },
    {
        "text": " The",
        "timestamp": [
            34.06,
            34.16
        ]
    },
    {
        "text": " mountains",
        "timestamp": [
            34.16,
            34.6
        ]
    },
    {
        "text": " explained",
        "timestamp": [
            34.6,
            35.2
        ]
    },
    {
        "text": " their",
        "timestamp": [
            35.2,
            35.52
        ]
    },
    {
        "text": " desire",
        "timestamp": [
            35.52,
            35.88
        ]
    },
    {
        "text": " to",
        "timestamp": [
            35.88,
            36.1
        ]
    },
    {
        "text": " meet",
        "timestamp": [
            36.1,
            36.26
        ]
    },
    {
        "text": " the",
        "timestamp": [
            36.26,
            36.5
        ]
    },
    {
        "text": " moon,",
        "timestamp": [
            36.5,
            36.72
        ]
    },
    {
        "text": " but",
        "timestamp": [
            36.86,
            37.12
        ]
    },
    {
        "text": " how",
        "timestamp": [
            37.12,
            37.62
        ]
    },
    {
        "text": " they",
        "timestamp": [
            37.62,
            37.84
        ]
    },
    {
        "text": " had",
        "timestamp": [
            37.84,
            38.04
        ]
    },
    {
        "text": " grown",
        "timestamp": [
            38.04,
            38.28
        ]
    },
    {
        "text": " tired",
        "timestamp": [
            38.28,
            38.72
        ]
    },
    {
        "text": " and",
        "timestamp": [
            38.72,
            39.02
        ]
    },
    {
        "text": " felt",
        "timestamp": [
            39.02,
            39.18
        ]
    },
    {
        "text": " like",
        "timestamp": [
            39.18,
            39.48
        ]
    },
    {
        "text": " giving",
        "timestamp": [
            39.48,
            39.64
        ]
    },
    {
        "text": " up.",
        "timestamp": [
            39.64,
            40.0
        ]
    },
    {
        "text": " The",
        "timestamp": [
            40.4,
            40.6
        ]
    },
    {
        "text": " old",
        "timestamp": [
            40.6,
            40.82
        ]
    },
    {
        "text": " man",
        "timestamp": [
            40.82,
            41.02
        ]
    },
    {
        "text": " listened",
        "timestamp": [
            41.02,
            41.38
        ]
    },
    {
        "text": " carefully",
        "timestamp": [
            41.38,
            42.1
        ]
    },
    {
        "text": " and",
        "timestamp": [
            42.1,
            42.58
        ]
    },
    {
        "text": " told",
        "timestamp": [
            42.58,
            42.76
        ]
    },
    {
        "text": " them",
        "timestamp": [
            42.76,
            42.9
        ]
    },
    {
        "text": " that",
        "timestamp": [
            42.9,
            43.1
        ]
    },
    {
        "text": " they",
        "timestamp": [
            43.1,
            43.36
        ]
    },
    {
        "text": " could",
        "timestamp": [
            43.36,
            43.62
        ]
    },
    {
        "text": " achieve",
        "timestamp": [
            43.62,
            44.0
        ]
    },
    {
        "text": " their",
        "timestamp": [
            44.0,
            44.32
        ]
    },
    {
        "text": " dream",
        "timestamp": [
            44.32,
            44.6
        ]
    },
    {
        "text": " if",
        "timestamp": [
            44.6,
            45.04
        ]
    },
    {
        "text": " they",
        "timestamp": [
            45.04,
            45.38
        ]
    },
    {
        "text": " changed",
        "timestamp": [
            45.38,
            45.7
        ]
    },
    {
        "text": " their",
        "timestamp": [
            45.7,
            46.08
        ]
    },
    {
        "text": " perspective.",
        "timestamp": [
            46.08,
            46.78
        ]
    },
    {
        "text": " He",
        "timestamp": [
            47.96,
            48.22
        ]
    },
    {
        "text": " told",
        "timestamp": [
            48.22,
            48.42
        ]
    },
    {
        "text": " them",
        "timestamp": [
            48.42,
            48.58
        ]
    },
    {
        "text": " that",
        "timestamp": [
            48.58,
            48.8
        ]
    },
    {
        "text": " they",
        "timestamp": [
            48.8,
            48.98
        ]
    },
    {
        "text": " couldn't",
        "timestamp": [
            48.98,
            49.22
        ]
    },
    {
        "text": " physically",
        "timestamp": [
            49.22,
            49.66
        ]
    },
    {
        "text": " reach",
        "timestamp": [
            49.66,
            50.0
        ]
    },
    {
        "text": " the",
        "timestamp": [
            50.0,
            50.22
        ]
    },
    {
        "text": " moon,",
        "timestamp": [
            50.22,
            50.48
        ]
    },
    {
        "text": " but",
        "timestamp": [
            50.56,
            50.84
        ]
    },
    {
        "text": " they",
        "timestamp": [
            50.84,
            51.06
        ]
    },
    {
        "text": " could",
        "timestamp": [
            51.06,
            51.24
        ]
    },
    {
        "text": " enjoy",
        "timestamp": [
            51.24,
            51.56
        ]
    },
    {
        "text": " it",
        "timestamp": [
            51.56,
            51.74
        ]
    },
    {
        "text": " in",
        "timestamp": [
            51.74,
            51.84
        ]
    },
    {
        "text": " its",
        "timestamp": [
            51.84,
            52.02
        ]
    },
    {
        "text": " place.",
        "timestamp": [
            52.02,
            52.36
        ]
    },
    {
        "text": " He",
        "timestamp": [
            52.36,
            52.68
        ]
    },
    {
        "text": " encouraged",
        "timestamp": [
            52.68,
            53.18
        ]
    },
    {
        "text": " the",
        "timestamp": [
            53.18,
            53.4
        ]
    },
    {
        "text": " mountains",
        "timestamp": [
            53.4,
            53.7
        ]
    },
    {
        "text": " to",
        "timestamp": [
            53.7,
            54.12
        ]
    },
    {
        "text": " appreciate",
        "timestamp": [
            54.12,
            54.58
        ]
    },
    {
        "text": " the",
        "timestamp": [
            54.58,
            54.78
        ]
    },
    {
        "text": " moon's",
        "timestamp": [
            54.78,
            55.1
        ]
    },
    {
        "text": " beauty",
        "timestamp": [
            55.1,
            55.4
        ]
    },
    {
        "text": " from",
        "timestamp": [
            55.4,
            55.78
        ]
    },
    {
        "text": " where",
        "timestamp": [
            55.78,
            56.18
        ]
    },
    {
        "text": " they",
        "timestamp": [
            56.18,
            56.6
        ]
    },
    {
        "text": " were",
        "timestamp": [
            56.6,
            57.0
        ]
    },
    {
        "text": " and",
        "timestamp": [
            57.0,
            57.7
        ]
    },
    {
        "text": " to",
        "timestamp": [
            57.7,
            58.16
        ]
    },
    {
        "text": " find",
        "timestamp": [
            58.16,
            58.4
        ]
    },
    {
        "text": " joy",
        "timestamp": [
            58.4,
            58.6
        ]
    },
    {
        "text": " in",
        "timestamp": [
            58.6,
            58.78
        ]
    },
    {
        "text": " the",
        "timestamp": [
            58.78,
            58.86
        ]
    },
    {
        "text": " journey",
        "timestamp": [
            58.86,
            59.2
        ]
    },
    {
        "text": " of",
        "timestamp": [
            59.2,
            59.46
        ]
    },
    {
        "text": " climbing",
        "timestamp": [
            59.46,
            59.98
        ]
    },
    {
        "text": " towards",
        "timestamp": [
            59.98,
            60.44
        ]
    },
    {
        "text": " it.",
        "timestamp": [
            60.44,
            61.36
        ]
    },
    {
        "text": " The",
        "timestamp": [
            62.28,
            62.4
        ]
    },
    {
        "text": " mountains",
        "timestamp": [
            62.4,
            62.74
        ]
    },
    {
        "text": " were",
        "timestamp": [
            62.74,
            63.02
        ]
    },
    {
        "text": " puzzled,",
        "timestamp": [
            63.02,
            63.42
        ]
    },
    {
        "text": " but",
        "timestamp": [
            63.52,
            63.64
        ]
    },
    {
        "text": " the",
        "timestamp": [
            63.64,
            63.84
        ]
    },
    {
        "text": " old",
        "timestamp": [
            63.84,
            64.0
        ]
    },
    {
        "text": " man",
        "timestamp": [
            64.0,
            64.3
        ]
    },
    {
        "text": " explained",
        "timestamp": [
            64.3,
            64.78
        ]
    },
    {
        "text": " that",
        "timestamp": [
            64.78,
            64.96
        ]
    },
    {
        "text": " they",
        "timestamp": [
            64.96,
            65.14
        ]
    },
    {
        "text": " didn't",
        "timestamp": [
            65.14,
            65.32
        ]
    },
    {
        "text": " need",
        "timestamp": [
            65.32,
            65.54
        ]
    },
    {
        "text": " to",
        "timestamp": [
            65.54,
            65.76
        ]
    },
    {
        "text": " physically",
        "timestamp": [
            65.76,
            66.0
        ]
    },
    {
        "text": " touch",
        "timestamp": [
            66.0,
            66.28
        ]
    },
    {
        "text": " the",
        "timestamp": [
            66.28,
            66.48
        ]
    },
    {
        "text": " moon",
        "timestamp": [
            66.48,
            66.62
        ]
    },
    {
        "text": " to",
        "timestamp": [
            66.62,
            66.92
        ]
    },
    {
        "text": " appreciate",
        "timestamp": [
            66.92,
            67.3
        ]
    },
    {
        "text": " its",
        "timestamp": [
            67.3,
            67.56
        ]
    },
    {
        "text": " beauty.",
        "timestamp": [
            67.56,
            67.9
        ]
    },
    {
        "text": " He",
        "timestamp": [
            68.24,
            68.52
        ]
    },
    {
        "text": " reminded",
        "timestamp": [
            68.52,
            68.8
        ]
    },
    {
        "text": " them",
        "timestamp": [
            68.8,
            69.04
        ]
    },
    {
        "text": " that",
        "timestamp": [
            69.04,
            69.26
        ]
    },
    {
        "text": " they",
        "timestamp": [
            69.26,
            69.4
        ]
    },
    {
        "text": " were",
        "timestamp": [
            69.4,
            69.62
        ]
    },
    {
        "text": " already",
        "timestamp": [
            69.62,
            69.92
        ]
    },
    {
        "text": " in",
        "timestamp": [
            69.92,
            70.08
        ]
    },
    {
        "text": " a",
        "timestamp": [
            70.08,
            70.16
        ]
    },
    {
        "text": " beautiful",
        "timestamp": [
            70.16,
            70.48
        ]
    },
    {
        "text": " place",
        "timestamp": [
            70.48,
            70.9
        ]
    },
    {
        "text": " surrounded",
        "timestamp": [
            70.9,
            71.36
        ]
    },
    {
        "text": " by",
        "timestamp": [
            71.36,
            71.66
        ]
    },
    {
        "text": " trees,",
        "timestamp": [
            71.66,
            72.0
        ]
    },
    {
        "text": " rivers,",
        "timestamp": [
            72.16,
            72.46
        ]
    },
    {
        "text": " and",
        "timestamp": [
            72.54,
            72.78
        ]
    },
    {
        "text": " valleys,",
        "timestamp": [
            72.78,
            73.06
        ]
    },
    {
        "text": " and",
        "timestamp": [
            73.06,
            73.48
        ]
    },
    {
        "text": " that",
        "timestamp": [
            73.48,
            73.64
        ]
    },
    {
        "text": " the",
        "timestamp": [
            73.64,
            73.9
        ]
    },
    {
        "text": " moon",
        "timestamp": [
            73.9,
            74.14
        ]
    },
    {
        "text": " would",
        "timestamp": [
            74.14,
            74.38
        ]
    },
    {
        "text": " be",
        "timestamp": [
            74.38,
            74.62
        ]
    },
    {
        "text": " a",
        "timestamp": [
            74.62,
            74.78
        ]
    },
    {
        "text": " great",
        "timestamp": [
            74.78,
            74.9
        ]
    },
    {
        "text": " addition",
        "timestamp": [
            74.9,
            75.36
        ]
    },
    {
        "text": " to",
        "timestamp": [
            75.36,
            75.6
        ]
    },
    {
        "text": " their",
        "timestamp": [
            75.6,
            75.94
        ]
    },
    {
        "text": " view.",
        "timestamp": [
            75.94,
            76.3
        ]
    },
    {
        "text": " From",
        "timestamp": [
            77.2,
            77.46
        ]
    },
    {
        "text": " that",
        "timestamp": [
            77.46,
            77.74
        ]
    },
    {
        "text": " day",
        "timestamp": [
            77.74,
            77.96
        ]
    },
    {
        "text": " on,",
        "timestamp": [
            77.96,
            78.2
        ]
    },
    {
        "text": " the",
        "timestamp": [
            78.38,
            78.52
        ]
    },
    {
        "text": " mountains",
        "timestamp": [
            78.52,
            78.82
        ]
    },
    {
        "text": " and",
        "timestamp": [
            78.82,
            78.96
        ]
    },
    {
        "text": " the",
        "timestamp": [
            78.96,
            79.14
        ]
    },
    {
        "text": " moon",
        "timestamp": [
            79.14,
            79.24
        ]
    },
    {
        "text": " became",
        "timestamp": [
            79.24,
            79.6
        ]
    },
    {
        "text": " great",
        "timestamp": [
            79.6,
            79.96
        ]
    },
    {
        "text": " friends.",
        "timestamp": [
            79.96,
            80.42
        ]
    },
    {
        "text": " The",
        "timestamp": [
            80.42,
            80.94
        ]
    },
    {
        "text": " mountains",
        "timestamp": [
            80.94,
            81.2
        ]
    },
    {
        "text": " appreciated",
        "timestamp": [
            81.2,
            81.84
        ]
    },
    {
        "text": " the",
        "timestamp": [
            81.84,
            82.08
        ]
    },
    {
        "text": " moon's",
        "timestamp": [
            82.08,
            82.38
        ]
    },
    {
        "text": " beauty",
        "timestamp": [
            82.38,
            82.58
        ]
    },
    {
        "text": " every",
        "timestamp": [
            82.58,
            83.22
        ]
    },
    {
        "text": " night",
        "timestamp": [
            83.22,
            83.72
        ]
    },
    {
        "text": " and",
        "timestamp": [
            83.72,
            84.16
        ]
    },
    {
        "text": " were",
        "timestamp": [
            84.16,
            84.36
        ]
    },
    {
        "text": " grateful",
        "timestamp": [
            84.36,
            84.58
        ]
    },
    {
        "text": " for",
        "timestamp": [
            84.58,
            84.86
        ]
    },
    {
        "text": " the",
        "timestamp": [
            84.86,
            85.02
        ]
    },
    {
        "text": " old",
        "timestamp": [
            85.02,
            85.2
        ]
    },
    {
        "text": " man's",
        "timestamp": [
            85.2,
            85.86
        ]
    },
    {
        "text": " wise",
        "timestamp": [
            85.86,
            86.06
        ]
    },
    {
        "text": " words.",
        "timestamp": [
            86.06,
            86.52
        ]
    },
    {
        "text": " They",
        "timestamp": [
            86.82,
            87.02
        ]
    },
    {
        "text": " learned",
        "timestamp": [
            87.02,
            87.16
        ]
    },
    {
        "text": " an",
        "timestamp": [
            87.16,
            87.42
        ]
    },
    {
        "text": " important",
        "timestamp": [
            87.42,
            87.64
        ]
    },
    {
        "text": " lesson",
        "timestamp": [
            87.64,
            87.92
        ]
    },
    {
        "text": " about",
        "timestamp": [
            87.92,
            88.12
        ]
    },
    {
        "text": " perspective",
        "timestamp": [
            88.12,
            88.56
        ]
    },
    {
        "text": " and",
        "timestamp": [
            88.56,
            88.84
        ]
    },
    {
        "text": " finding",
        "timestamp": [
            88.84,
            89.08
        ]
    },
    {
        "text": " joy",
        "timestamp": [
            89.08,
            89.48
        ]
    },
    {
        "text": " in",
        "timestamp": [
            89.48,
            89.84
        ]
    },
    {
        "text": " the",
        "timestamp": [
            89.84,
            90.08
        ]
    },
    {
        "text": " journey.",
        "timestamp": [
            90.08,
            90.4
        ]
    },
    {
        "text": " So",
        "timestamp": [
            91.22,
            91.38
        ]
    },
    {
        "text": " the",
        "timestamp": [
            91.38,
            91.48
        ]
    },
    {
        "text": " lesson",
        "timestamp": [
            91.48,
            91.74
        ]
    },
    {
        "text": " here",
        "timestamp": [
            91.74,
            92.0
        ]
    },
    {
        "text": " is",
        "timestamp": [
            92.0,
            92.2
        ]
    },
    {
        "text": " to",
        "timestamp": [
            92.2,
            92.4
        ]
    },
    {
        "text": " find",
        "timestamp": [
            92.4,
            92.6
        ]
    },
    {
        "text": " joy",
        "timestamp": [
            92.6,
            92.88
        ]
    },
    {
        "text": " in",
        "timestamp": [
            92.88,
            93.08
        ]
    },
    {
        "text": " the",
        "timestamp": [
            93.08,
            93.24
        ]
    },
    {
        "text": " journey",
        "timestamp": [
            93.24,
            93.44
        ]
    },
    {
        "text": " that",
        "timestamp": [
            93.44,
            93.8
        ]
    },
    {
        "text": " you",
        "timestamp": [
            93.8,
            94.06
        ]
    },
    {
        "text": " are",
        "timestamp": [
            94.06,
            94.38
        ]
    },
    {
        "text": " in",
        "timestamp": [
            94.38,
            94.6
        ]
    },
    {
        "text": " and",
        "timestamp": [
            94.6,
            94.96
        ]
    },
    {
        "text": " not",
        "timestamp": [
            94.96,
            95.26
        ]
    },
    {
        "text": " anyone",
        "timestamp": [
            95.26,
            95.6
        ]
    },
    {
        "text": " else's.",
        "timestamp": [
            95.6,
            96.08
        ]
    }
]